twindb_cloudflare/__init__.py
twindb_cloudflare/twindb_cloudflare.py
twindb_cloudflare-0.1.1.dist-info/DESCRIPTION.rst
twindb_cloudflare-0.1.1.dist-info/METADATA
twindb_cloudflare-0.1.1.dist-info/RECORD
twindb_cloudflare-0.1.1.dist-info/WHEEL
twindb_cloudflare-0.1.1.dist-info/metadata.json
twindb_cloudflare-0.1.1.dist-info/top_level.txt
