Metadata-Version: 2.0
Name: twindb-cloudflare
Version: 0.1.1
Summary: TwinDB CloudFlare Library is a module to work with CloudFlare API
Home-page: https://github.com/twindb/twindb_cloudflare
Author: TwinDB Development Team
Author-email: dev@twindb.com
License: Apache Software License 2.0
Keywords: twindb_cloudflare
Platform: UNKNOWN
Classifier: Development Status :: 2 - Pre-Alpha
Classifier: Intended Audience :: Developers
Classifier: License :: OSI Approved :: Apache Software License
Classifier: Natural Language :: English
Classifier: Programming Language :: Python :: 2
Classifier: Programming Language :: Python :: 2.6
Classifier: Programming Language :: Python :: 2.7
Classifier: Programming Language :: Python :: 3
Classifier: Programming Language :: Python :: 3.3
Classifier: Programming Language :: Python :: 3.4
Classifier: Programming Language :: Python :: 3.5
